{
"meta":{"test_sets":[],"test_metrics":[],"learn_metrics":[{"best_value":"Min","name":"Logloss"}],"launch_mode":"Train","parameters":"","iteration_count":220,"learn_sets":["learn"],"name":"experiment"},
"iterations":[
{"learn":[0.3765869613],"iteration":0,"passed_time":0.08450037264,"remaining_time":18.50558161},
{"learn":[0.3394921327],"iteration":1,"passed_time":0.1171116051,"remaining_time":12.76516496},
{"learn":[0.2885138889],"iteration":2,"passed_time":0.1448694468,"remaining_time":10.47888998},
{"learn":[0.2679795336],"iteration":3,"passed_time":0.1717579642,"remaining_time":9.274930068},
{"learn":[0.2583884566],"iteration":4,"passed_time":0.1972851274,"remaining_time":8.48326048},
{"learn":[0.2493900833],"iteration":5,"passed_time":0.2299136027,"remaining_time":8.200251828},
{"learn":[0.2343257369],"iteration":6,"passed_time":0.2566975123,"remaining_time":7.810938589},
{"learn":[0.2264796906],"iteration":7,"passed_time":0.2828598153,"remaining_time":7.495785106},
{"learn":[0.217241102],"iteration":8,"passed_time":0.3090309295,"remaining_time":7.245058458},
{"learn":[0.2122895954],"iteration":9,"passed_time":0.3394614778,"remaining_time":7.128691033},
{"learn":[0.2076371973],"iteration":10,"passed_time":0.3659817952,"remaining_time":6.953654109},
{"learn":[0.2036181907],"iteration":11,"passed_time":0.3915800392,"remaining_time":6.787387345},
{"learn":[0.2005498902],"iteration":12,"passed_time":0.4186938184,"remaining_time":6.666893877},
{"learn":[0.1988939302],"iteration":13,"passed_time":0.4442926023,"remaining_time":6.537448291},
{"learn":[0.1944459925],"iteration":14,"passed_time":0.4701001833,"remaining_time":6.424702505},
{"learn":[0.1913107275],"iteration":15,"passed_time":0.4988177047,"remaining_time":6.359925736},
{"learn":[0.1883717529],"iteration":16,"passed_time":0.5262991102,"remaining_time":6.284630551},
{"learn":[0.1876130155],"iteration":17,"passed_time":0.5530531473,"remaining_time":6.20648532},
{"learn":[0.1796172398],"iteration":18,"passed_time":0.5824260593,"remaining_time":6.161454628},
{"learn":[0.1701471753],"iteration":19,"passed_time":0.6096201288,"remaining_time":6.096201288},
{"learn":[0.1689802355],"iteration":20,"passed_time":0.6367192073,"remaining_time":6.033672489},
{"learn":[0.1654290755],"iteration":21,"passed_time":0.6627034653,"remaining_time":5.964331188},
{"learn":[0.1646371207],"iteration":22,"passed_time":0.688046724,"remaining_time":5.893269766},
{"learn":[0.1615308264],"iteration":23,"passed_time":0.7161678508,"remaining_time":5.848704115},
{"learn":[0.1583610893],"iteration":24,"passed_time":0.7429382136,"remaining_time":5.794918066},
{"learn":[0.1579750905],"iteration":25,"passed_time":0.7690559157,"remaining_time":5.738340294},
{"learn":[0.1564120264],"iteration":26,"passed_time":0.794636947,"remaining_time":5.680182621},
{"learn":[0.1511466493],"iteration":27,"passed_time":0.8222440278,"remaining_time":5.638244762},
{"learn":[0.1495459452],"iteration":28,"passed_time":0.8491329762,"remaining_time":5.592565464},
{"learn":[0.1459628321],"iteration":29,"passed_time":0.8757370618,"remaining_time":5.546334725},
{"learn":[0.1399330744],"iteration":30,"passed_time":0.9043370112,"remaining_time":5.513538552},
{"learn":[0.1382173128],"iteration":31,"passed_time":0.9340110666,"remaining_time":5.487315016},
{"learn":[0.1374514482],"iteration":32,"passed_time":0.9601433718,"remaining_time":5.44081244},
{"learn":[0.1372446074],"iteration":33,"passed_time":0.9855956231,"remaining_time":5.391787821},
{"learn":[0.1341859804],"iteration":34,"passed_time":1.018298374,"remaining_time":5.382434261},
{"learn":[0.1338581299],"iteration":35,"passed_time":1.043917026,"remaining_time":5.335575912},
{"learn":[0.1325095783],"iteration":36,"passed_time":1.069943468,"remaining_time":5.29188256},
{"learn":[0.1302746431],"iteration":37,"passed_time":1.097959573,"remaining_time":5.25864848},
{"learn":[0.1300042826],"iteration":38,"passed_time":1.125545097,"remaining_time":5.223683657},
{"learn":[0.1289190951],"iteration":39,"passed_time":1.152167194,"remaining_time":5.184752371},
{"learn":[0.1287766446],"iteration":40,"passed_time":1.17771102,"remaining_time":5.141713963},
{"learn":[0.1273267765],"iteration":41,"passed_time":1.20329465,"remaining_time":5.099677328},
{"learn":[0.1262653192],"iteration":42,"passed_time":1.232175512,"remaining_time":5.071978272},
{"learn":[0.1243656303],"iteration":43,"passed_time":1.258448618,"remaining_time":5.033794474},
{"learn":[0.1241489828],"iteration":44,"passed_time":1.284240174,"remaining_time":4.994267345},
{"learn":[0.1240341119],"iteration":45,"passed_time":1.309806867,"remaining_time":4.954486845},
{"learn":[0.1191986964],"iteration":46,"passed_time":1.341595627,"remaining_time":4.938213693},
{"learn":[0.1173451973],"iteration":47,"passed_time":1.368075754,"remaining_time":4.902271452},
{"learn":[0.1172348218],"iteration":48,"passed_time":1.397460461,"remaining_time":4.876851815},
{"learn":[0.1167411863],"iteration":49,"passed_time":1.427288494,"remaining_time":4.852780879},
{"learn":[0.1128149082],"iteration":50,"passed_time":1.466450358,"remaining_time":4.859413932},
{"learn":[0.1111982875],"iteration":51,"passed_time":1.49693164,"remaining_time":4.836240683},
{"learn":[0.111039637],"iteration":52,"passed_time":1.52842759,"remaining_time":4.81598882},
{"learn":[0.1094247138],"iteration":53,"passed_time":1.555309457,"remaining_time":4.781136479},
{"learn":[0.1083131596],"iteration":54,"passed_time":1.581206585,"remaining_time":4.743619756},
{"learn":[0.1082183237],"iteration":55,"passed_time":1.606492719,"remaining_time":4.704728676},
{"learn":[0.1072301826],"iteration":56,"passed_time":1.638499907,"remaining_time":4.685534821},
{"learn":[0.1070897776],"iteration":57,"passed_time":1.665154544,"remaining_time":4.650948899},
{"learn":[0.1052923293],"iteration":58,"passed_time":1.69186146,"remaining_time":4.616774492},
{"learn":[0.1048206427],"iteration":59,"passed_time":1.722065642,"remaining_time":4.592175046},
{"learn":[0.1022172741],"iteration":60,"passed_time":1.749836457,"remaining_time":4.561049126},
{"learn":[0.1015269463],"iteration":61,"passed_time":1.77669748,"remaining_time":4.527712933},
{"learn":[0.1005268968],"iteration":62,"passed_time":1.802668743,"remaining_time":4.492364964},
{"learn":[0.09919696925],"iteration":63,"passed_time":1.829704669,"remaining_time":4.459905131},
{"learn":[0.09875827333],"iteration":64,"passed_time":1.856171203,"remaining_time":4.426254406},
{"learn":[0.09869757736],"iteration":65,"passed_time":1.88152539,"remaining_time":4.390225909},
{"learn":[0.09857480505],"iteration":66,"passed_time":1.907070153,"remaining_time":4.354951244},
{"learn":[0.09791710315],"iteration":67,"passed_time":1.938572393,"remaining_time":4.333279466},
{"learn":[0.09729250447],"iteration":68,"passed_time":1.964290237,"remaining_time":4.298664142},
{"learn":[0.09609789015],"iteration":69,"passed_time":1.991280776,"remaining_time":4.267030235},
{"learn":[0.09482076011],"iteration":70,"passed_time":2.024817245,"remaining_time":4.249264359},
{"learn":[0.09282800789],"iteration":71,"passed_time":2.052159443,"remaining_time":4.218327744},
{"learn":[0.09221035761],"iteration":72,"passed_time":2.078015173,"remaining_time":4.184496307},
{"learn":[0.09208094422],"iteration":73,"passed_time":2.103190761,"remaining_time":4.149538529},
{"learn":[0.09147638545],"iteration":74,"passed_time":2.130792421,"remaining_time":4.119532014},
{"learn":[0.09114732044],"iteration":75,"passed_time":2.156353684,"remaining_time":4.08572277},
{"learn":[0.09039109275],"iteration":76,"passed_time":2.18319054,"remaining_time":4.054496716},
{"learn":[0.09010975666],"iteration":77,"passed_time":2.209316249,"remaining_time":4.022088555},
{"learn":[0.0900639039],"iteration":78,"passed_time":2.240308211,"remaining_time":3.998524782},
{"learn":[0.08996586163],"iteration":79,"passed_time":2.265262742,"remaining_time":3.964209799},
{"learn":[0.08964180116],"iteration":80,"passed_time":2.291263699,"remaining_time":3.931921657},
{"learn":[0.08922333471],"iteration":81,"passed_time":2.321347973,"remaining_time":3.906658784},
{"learn":[0.089171372],"iteration":82,"passed_time":2.350080933,"remaining_time":3.879049251},
{"learn":[0.08872689083],"iteration":83,"passed_time":2.376335466,"remaining_time":3.847400279},
{"learn":[0.08808056489],"iteration":84,"passed_time":2.402816945,"remaining_time":3.816238677},
{"learn":[0.08738604204],"iteration":85,"passed_time":2.431246538,"remaining_time":3.788221349},
{"learn":[0.08686203146],"iteration":86,"passed_time":2.458443425,"remaining_time":3.758310063},
{"learn":[0.08620800909],"iteration":87,"passed_time":2.485170032,"remaining_time":3.727755049},
{"learn":[0.08602456506],"iteration":88,"passed_time":2.510669979,"remaining_time":3.695480531},
{"learn":[0.08570232681],"iteration":89,"passed_time":2.544347911,"remaining_time":3.675169204},
{"learn":[0.08566998113],"iteration":90,"passed_time":2.571833735,"remaining_time":3.645786284},
{"learn":[0.08526965741],"iteration":91,"passed_time":2.59831776,"remaining_time":3.615050797}
]}